collector/__init__.py
collector/__main__.py
collector/config.py
collector/orchestrator.py
collector/validators.py
collector/core/__init__.py
collector/core/base.py
collector/core/cisco_collector.py
collector/core/metadata.py
hvt6/__init__.py
hvt6/__main__.py
hvt6/__version__.py
hvt6/cli.py
hvt6/collector_cli.py
hvt6/checks/__init__.py
hvt6/checks/base.py
hvt6/checks/registry.py
hvt6/checks/aaa/__init__.py
hvt6/checks/aaa/composite.py
hvt6/checks/control/__init__.py
hvt6/checks/control/bgp_security.py
hvt6/checks/control/eigrp_auth.py
hvt6/checks/control/infrastructure_acl.py
hvt6/checks/control/ospf_auth.py
hvt6/checks/data/__init__.py
hvt6/checks/data/unused_interfaces.py
hvt6/checks/management/__init__.py
hvt6/checks/management/ssh_security.py
hvt6/checks/management/ssh_vty_unified.py
hvt6/checks/management/vty_security.py
hvt6/checks/snmp/__init__.py
hvt6/checks/snmp/community.py
hvt6/checks/snmp/trap.py
hvt6/core/__init__.py
hvt6/core/config.py
hvt6/core/credentials.py
hvt6/core/enums.py
hvt6/core/exceptions.py
hvt6/core/models.py
hvt6/devices/__init__.py
hvt6/reporting/__init__.py
hvt6/reporting/builder.py
hvt6/reporting/excel_generator.py
hvt6/reporting/pdf_generator.py
hvt6/reporting/tabular_generator.py
hvt6/reporting/formatters/__init__.py
hvt6/scoring/__init__.py
hvt6/scoring/calculator.py
hvt6/utils/__init__.py
hvt6-6.5.3.dist-info/licenses/LICENSE
hvt6-6.5.3.dist-info/METADATA
hvt6-6.5.3.dist-info/WHEEL
hvt6-6.5.3.dist-info/entry_points.txt
hvt6-6.5.3.dist-info/top_level.txt
hvt6-6.5.3.dist-info/RECORD
