Metadata-Version: 2.4
Name: hvt6
Version: 6.5.3
Summary: Automated security hardening verification tool for Cisco IOS, IOS-XE, and NX-OS devices
Author-email: Nicolas Padin <npadin@example.com>
Maintainer-email: Nicolas Padin <npadin@example.com>
License: GPL-3.0-or-later
Project-URL: Homepage, https://github.com/npadin/ios-xe_hardening
Project-URL: Documentation, https://github.com/npadin/ios-xe_hardening/blob/main/README.md
Project-URL: Repository, https://github.com/npadin/ios-xe_hardening
Project-URL: Issues, https://github.com/npadin/ios-xe_hardening/issues
Project-URL: Changelog, https://github.com/npadin/ios-xe_hardening/blob/main/CHANGELOG.md
Project-URL: Source Code, https://github.com/npadin/ios-xe_hardening
Keywords: cisco,ios-xe,ios,nx-os,network-security,configuration-audit,hardening,security-compliance,cisco-ios,network-automation,security-audit,cisco-hardening,nist,cis-benchmark,stig
Classifier: Development Status :: 5 - Production/Stable
Classifier: Intended Audience :: System Administrators
Classifier: Intended Audience :: Information Technology
Classifier: Intended Audience :: Telecommunications Industry
Classifier: Topic :: System :: Networking
Classifier: Topic :: Security
Classifier: Topic :: System :: Systems Administration
Classifier: License :: OSI Approved :: GNU General Public License v3 or later (GPLv3+)
Classifier: Programming Language :: Python :: 3
Classifier: Programming Language :: Python :: 3.8
Classifier: Programming Language :: Python :: 3.9
Classifier: Programming Language :: Python :: 3.10
Classifier: Programming Language :: Python :: 3.11
Classifier: Programming Language :: Python :: 3.12
Classifier: Operating System :: OS Independent
Classifier: Environment :: Console
Classifier: Natural Language :: Spanish
Classifier: Natural Language :: English
Requires-Python: >=3.8
License-File: LICENSE
Requires-Dist: ciscoconfparse2>=0.8.7
Requires-Dist: jinja2>=3.1.6
Requires-Dist: pyyaml>=6.0.2
Requires-Dist: python-dotenv>=1.1.0
Requires-Dist: loguru>=0.7.3
Requires-Dist: colorama>=0.4.6
Requires-Dist: rich>=14.0.0
Requires-Dist: tabulate>=0.9.0
Requires-Dist: pandas>=2.2.3
Requires-Dist: openpyxl>=3.1.2
Provides-Extra: pdf
Requires-Dist: weasyprint>=66.0; extra == "pdf"
Requires-Dist: pypdf>=5.4.0; extra == "pdf"
Requires-Dist: reportlab>=4.3.1; extra == "pdf"
Provides-Extra: collector
Requires-Dist: nornir>=3.5.0; extra == "collector"
Requires-Dist: nornir-netmiko>=1.0.1; extra == "collector"
Requires-Dist: nornir-utils>=0.2.0; extra == "collector"
Requires-Dist: netmiko>=4.5.0; extra == "collector"
Requires-Dist: paramiko>=3.5.1; extra == "collector"
Requires-Dist: tenacity>=9.1.2; extra == "collector"
Requires-Dist: tqdm>=4.67.1; extra == "collector"
Provides-Extra: all
Requires-Dist: weasyprint>=66.0; extra == "all"
Requires-Dist: pypdf>=5.4.0; extra == "all"
Requires-Dist: reportlab>=4.3.1; extra == "all"
Requires-Dist: nornir>=3.5.0; extra == "all"
Requires-Dist: nornir-netmiko>=1.0.1; extra == "all"
Requires-Dist: nornir-utils>=0.2.0; extra == "all"
Requires-Dist: netmiko>=4.5.0; extra == "all"
Requires-Dist: paramiko>=3.5.1; extra == "all"
Requires-Dist: tenacity>=9.1.2; extra == "all"
Requires-Dist: tqdm>=4.67.1; extra == "all"
Provides-Extra: dev
Requires-Dist: pytest>=7.0; extra == "dev"
Requires-Dist: pytest-cov>=4.0; extra == "dev"
Requires-Dist: black>=23.0; extra == "dev"
Requires-Dist: ruff>=0.1.0; extra == "dev"
Requires-Dist: mypy>=1.0; extra == "dev"
Requires-Dist: build>=1.0; extra == "dev"
Requires-Dist: twine>=4.0; extra == "dev"
Requires-Dist: check-manifest>=0.49; extra == "dev"
Dynamic: license-file
